pupil_labs/pupil_core_network_client/__init__.py
pupil_labs/pupil_core_network_client/decorators.py
pupil_labs/pupil_core_network_client/device.py
pupil_labs/pupil_core_network_client/subscription.py
pupil_core_network_client-1.0.0a5.dist-info/LICENSE
pupil_core_network_client-1.0.0a5.dist-info/METADATA
pupil_core_network_client-1.0.0a5.dist-info/WHEEL
pupil_core_network_client-1.0.0a5.dist-info/top_level.txt
pupil_core_network_client-1.0.0a5.dist-info/RECORD
