Metadata-Version: 2.1
Name: pupil-core-network-client
Version: 1.0.0a5
Summary: A Python client for the Pupil Core Network API
Home-page: https://github.com/papr/pupil-core-network-client
Author: Pupil Labs GmbH
Author-email: info@pupil-labs.com
License: MIT
Classifier: Development Status :: 3 - Alpha
Classifier: Intended Audience :: Developers
Classifier: License :: OSI Approved :: MIT License
Classifier: Programming Language :: Python :: 3
Classifier: Programming Language :: Python :: 3 :: Only
Requires-Python: >=3.7
License-File: LICENSE
Requires-Dist: msgpack (>=1.0.0)
Requires-Dist: pyzmq
Requires-Dist: importlib-metadata ; python_version < "3.8"
Requires-Dist: typing-extensions ; python_version < "3.8"
Provides-Extra: docs
Requires-Dist: furo ; extra == 'docs'
Requires-Dist: jaraco.packaging (>=8.2) ; extra == 'docs'
Requires-Dist: rst.linker (>=1.9) ; extra == 'docs'
Requires-Dist: sphinx ; extra == 'docs'
Provides-Extra: examples
Requires-Dist: numpy ; extra == 'examples'
Provides-Extra: testing
Requires-Dist: pytest (>=6) ; extra == 'testing'
Requires-Dist: pytest-checkdocs (>=2.4) ; extra == 'testing'
Requires-Dist: pytest-cov ; extra == 'testing'
Requires-Dist: pytest-enabler (>=1.0.1) ; extra == 'testing'
Requires-Dist: pytest-mypy ; extra == 'testing'
